umobj/__init__.py
umobj/acl.py
umobj/bucket.py
umobj/compat.py
umobj/email_utils.py
umobj/handler_queue.py
umobj/key.py
umobj/md5.py
umobj/multipart.py
umobj/obj.py
umobj/options.py
umobj/tar.py
umobj/transfer.py
umobj/utils.py
umobj/verify.py
umobj-3.0.2.data/scripts/bagobj
umobj-3.0.2.data/scripts/catobj
umobj-3.0.2.data/scripts/chobj
umobj-3.0.2.data/scripts/cmpobj
umobj-3.0.2.data/scripts/cpobj
umobj-3.0.2.data/scripts/lsobj
umobj-3.0.2.data/scripts/mkobj
umobj-3.0.2.data/scripts/mvobj
umobj-3.0.2.data/scripts/rmobj
umobj-3.0.2.data/scripts/streamobj
umobj-3.0.2.data/scripts/syncobj
umobj-3.0.2.data/scripts/webobj
umobj-3.0.2.dist-info/LICENSE
umobj-3.0.2.dist-info/METADATA
umobj-3.0.2.dist-info/WHEEL
umobj-3.0.2.dist-info/top_level.txt
umobj-3.0.2.dist-info/RECORD
