Metadata-Version: 2.1
Name: umobj
Version: 3.0.2
Summary: UMIACS Object Storage Commands
Home-page: https://github.com/UMIACS/umobj
Author: UMIACS Staff
Author-email: github@umiacs.umd.edu
License: LGPL v2.1
Platform: Posix; MacOS X; Windows
Classifier: Development Status :: 5 - Production/Stable
Classifier: Operating System :: OS Independent
Classifier: Topic :: Internet
Classifier: Programming Language :: Python :: 2
Classifier: Programming Language :: Python :: 2.7
Classifier: Programming Language :: Python :: 3
Classifier: Programming Language :: Python :: 3.6
Classifier: Programming Language :: Python :: 3.7
Requires-Dist: boto (>=2.49.0)
Requires-Dist: filechunkio
Requires-Dist: progressbar
Requires-Dist: qav
Requires-Dist: bagit (>=1.7.0)
Requires-Dist: certifi (>=2019.11.28)
